{
  "level_id": 12,
  "name": "Full Adder",
  "description": "A Full-Adder adds A + B + CarryIn and outputs Sum + CarryOut.\nThis is the core building block of CPUs for arithmetic",
  "difficulty": "Medium",
  "objectives": ["Build a full-adder using two half adders and one or gate"],
  "components": [
    {"type": "Input", "position": [0,1], "immovable": true, "label": "A"},
    {"type": "Input", "position": [0,3], "immovable": true, "label": "B"},
    {"type": "Input", "position": [0,5], "immovable": true, "label": "CarryIn"},
    {"type": "Output", "position":  [4, 2], "immovable":  true, "label":  "Sum"},
    {"type": "Output", "position":  [4, 4], "immovable":  true, "label":  "CarryOut"}
  ],
  "available_components": [
    {"type":  "HalfAdder"},
    {"type": "Or"}
  ],
  "hints": [
    "A Full Adder needs to add three bits: A, B, and CarryIn",
    "Use the first Half Adder to add A and B together",
    "Use the second Half Adder to add the Sum from the first adder with CarryIn",
    "If either Half Adder produces a carry, the final CarryOut should be 1",
    "Connect the carry outputs from both Half Adders to an OR gate"
  ],
  "solution": "",
  "tests": [
      {"inputs": [[0,1],[0,1],[0,1]], "expected_output": [[0,1],[0,1]]},
      {"inputs": [[0,1],[0,1],[1,1]], "expected_output": [[1,1],[0,1]]},
      {"inputs": [[0,1],[1,1],[0,1]], "expected_output": [[1,1],[0,1]]},
      {"inputs": [[0,1],[1,1],[1,1]], "expected_output": [[0,1],[1,1]]},
      {"inputs": [[1,1],[0,1],[0,1]], "expected_output": [[1,1],[0,1]]},
      {"inputs": [[1,1],[0,1],[1,1]], "expected_output": [[0,1],[1,1]]},
      {"inputs": [[1,1],[1,1],[0,1]], "expected_output": [[0,1],[1,1]]},
      {"inputs": [[1,1],[1,1],[1,1]], "expected_output": [[1,1],[1,1]]}
  ]
}